README.md
setup.py
timeliterals/__init__.py
timeliterals.egg-info/PKG-INFO
timeliterals.egg-info/SOURCES.txt
timeliterals.egg-info/dependency_links.txt
timeliterals.egg-info/top_level.txt