Metadata-Version: 1.0
Name: timeliterals
Version: 0.0.4
Summary: Time literals
Home-page: https://github.com/pgdr/timeliterals
Author: pgdr
Author-email: pgdr@equinor.com
License: UNKNOWN
Platform: UNKNOWN
